access/__init__.py
access/admin.py
access/managers.py
access/plugins.py
access/auth/__init__.py
access/auth/backends.py
django_access-0.1.2b1.dist-info/LICENSE
django_access-0.1.2b1.dist-info/METADATA
django_access-0.1.2b1.dist-info/WHEEL
django_access-0.1.2b1.dist-info/top_level.txt
django_access-0.1.2b1.dist-info/RECORD
